{
  "MenuItem": [
    {
    "pos" : 1,
    "Name" : "Main",
    "MenuItems" : [ "Licht", "Tür", "Kameras", "Schildis", "Einstellungen" ]
    },
 {
      "pos": 2,
      "Name": "Sensoren",
      "MenuItems": [ "Aussentemperatur", "Innentemperatur", "Temperatur Schildkrötenhaus", "Luftfeuchtigkeit aussen", "Wind" ],
      "Type": "sensor"
    },
  {
      "pos": 3,
      "Name": "Licht",
      "MenuItems": [ "Wohnzimmer Stehlampe", "Terasse", "Terasse Bodenleuchten" ],
      "Type": "switch"
    },
  {
      "pos": 4,
      "Name": "Schildis",
      "MenuItems": [ "UV-Licht", "Wärmelampe", "Frostwächter", "Heizmatte T&L", "Heizmatte Baby", "Tür vorne", "Tür mitte", "Tür hinten" ],
      "Type": "switch"
    },
 {
      "pos": 5,
      "Name": "Tür",
      "Type": "Form"
    },
    {
      "pos": 6,
      "Name": "Kameras",
      "Type": "Form"
    }
    ]
  }


 

 